nuisco/__init__.py
nuisco/build.py
nuisco/compile_libraries_v2.3.py
nuisco/convert_socket.py
nuisco/main.py
nuisco/make_socket.py
nuisco/template.py
nuisco/templates/ppat/ppat-config.json
nuisco/templates/ppt/.flake8
nuisco/templates/ppt/.gitignore
nuisco/templates/ppt/CONTRIBUTING.md
nuisco/templates/ppt/LICENSE
nuisco/templates/ppt/Makefile
nuisco/templates/ppt/README.md
nuisco/templates/ppt/build.bat
nuisco/templates/ppt/build.sh
nuisco/templates/ppt/create_dist.bat
nuisco/templates/ppt/create_dist.sh
nuisco/templates/ppt/dev-requirements.txt
nuisco/templates/ppt/inno_setup_script.iss
nuisco/templates/ppt/install.bat
nuisco/templates/ppt/install.sh
nuisco/templates/ppt/install_dist.bat
nuisco/templates/ppt/install_dist.sh
nuisco/templates/ppt/ppt-config.json
nuisco/templates/ppt/pylint.rc
nuisco/templates/ppt/run.bat
nuisco/templates/ppt/run.sh
nuisco/templates/ppt/scripts.sh
nuisco/templates/ppt/.github/workflows/ci.yml
nuisco/templates/ppt/data/Create_your_own.txt
nuisco/templates/ppt/data/logo-1.ico
nuisco/templates/ppt/data/logo-1.png
nuisco/templates/ppt/data/logo-2.ico
nuisco/templates/ppt/data/logo-2.png
nuisco/templates/ppt/data/logo-3.ico
nuisco/templates/ppt/data/logo-3.png
nuisco/templates/ppt/data/logo-4.ico
nuisco/templates/ppt/data/logo-4.png
nuisco/templates/ppt/data/logo-5.ico
nuisco/templates/ppt/data/logo-5.png
nuisco/templates/ppt/data/logo-6.ico
nuisco/templates/ppt/data/logo-6.png
nuisco/templates/ppt/data/logo-raw.ico
nuisco/templates/ppt/data/logo-raw.png
nuisco/templates/ppt/docs/classes.md
nuisco/templates/ppt/docs/gui.md
nuisco/templates/ppt/docs/link.md
nuisco/templates/ppt/docs/main.md
nuisco/templates/ppt/src/__init__.py
nuisco/templates/ppt/src/main.py
nuisco/templates/ppt/src/modules/classes.py
nuisco/templates/ppt/src/modules/gui.py
nuisco/templates/ppt/src/modules/link.py
nuisco/templates/ppt/src/modules/modulebase.py
nuisco/templates/ppt/tests/__init__.py
nuisco/templates/ppt/tests/test_main.py
nuisco-0.2.3.dist-info/LICENSE
nuisco-0.2.3.dist-info/METADATA
nuisco-0.2.3.dist-info/WHEEL
nuisco-0.2.3.dist-info/entry_points.txt
nuisco-0.2.3.dist-info/top_level.txt
nuisco-0.2.3.dist-info/RECORD
