Metadata-Version: 2.1
Name: nuisco
Version: 0.2.3
Summary: A faster and more customizable compiler based on nuitka
Author: Cariel Becker
License: GPL-3.0
Requires-Python: <3.12
License-File: LICENSE
Requires-Dist: nuitka ==1.8.4
Requires-Dist: aplustools
